fcmd/__init__.py
fcmd/cmd.py
fcmd/cmds.py
fcmd/reg.py
freg/__init__.py
freg/reg.py
pyFcmd-1.1.dist-info/DESCRIPTION.rst
pyFcmd-1.1.dist-info/METADATA
pyFcmd-1.1.dist-info/RECORD
pyFcmd-1.1.dist-info/WHEEL
pyFcmd-1.1.dist-info/metadata.json
pyFcmd-1.1.dist-info/top_level.txt
tests/__init__.py
tests/test.py
