Metadata-Version: 2.0
Name: pyFcmd
Version: 1.1
Summary: A pure Python library designed to show the information about what you specify on FREESWITCH
Home-page: https://github.com/sudaning/Fcmd
Author: Daning Su
Author-email: sudaning@sina.com
License: LICENSE
Platform: linux
Classifier: Development Status :: 5 - Production/Stable
Classifier: Intended Audience :: Science/Research
Classifier: Natural Language :: Chinese (Simplified)
Classifier: Topic :: Text Processing
Classifier: Operating System :: POSIX :: Linux
Classifier: License :: OSI Approved :: MIT License
Classifier: Programming Language :: Python :: 2
Classifier: Programming Language :: Python :: 2.7
Requires-Dist: pyFneko (>=3.4)
